MANIFEST.in
README.rst
setup.cfg
setup.py
fui/__init__.py
fui.locker.egg-info/PKG-INFO
fui.locker.egg-info/SOURCES.txt
fui.locker.egg-info/dependency_links.txt
fui.locker.egg-info/entry_points.txt
fui.locker.egg-info/namespace_packages.txt
fui.locker.egg-info/not-zip-safe
fui.locker.egg-info/paster_plugins.txt
fui.locker.egg-info/requires.txt
fui.locker.egg-info/top_level.txt
fui/locker/__init__.py
fui/locker/config.py
fui/locker/configure.zcml
fui/locker/interfaces.py
fui/locker/browser/__init__.py
fui/locker/browser/configure.zcml
fui/locker/browser/jquery.js
fui/locker/browser/lockerregistry_overview.pt
fui/locker/browser/lockerregistry_overview.py
fui/locker/browser/lockerreservation_form.pt
fui/locker/browser/lockerreservation_form.py
fui/locker/browser/lockerreservation_view.pt
fui/locker/browser/style.css
fui/locker/content/__init__.py
fui/locker/content/configure.zcml
fui/locker/content/lockerregistry.py
fui/locker/content/lockerreservation.py
fui/locker/profiles/default/catalog.xml
fui/locker/profiles/default/cssregistry.xml
fui/locker/profiles/default/factorytool.xml
fui/locker/profiles/default/jsregistry.xml
fui/locker/profiles/default/rolemap.xml
fui/locker/profiles/default/types.xml
fui/locker/profiles/default/types/LockerRegistry.xml
fui/locker/profiles/default/types/LockerReservation.xml
fui/locker/tests/__init__.py
fui/locker/tests/base.py
fui/locker/tests/test_doctest.py