Metadata-Version: 1.0
Name: fui.locker
Version: 1.3.0
Summary: UNKNOWN
Home-page: http://github.com/espenak/fui.locker
Author: Espen A. Kristiansen
Author-email: post@espenak.net
License: GPL
Platform: UNKNOWN
Classifier: Framework :: Plone
Classifier: Programming Language :: Python
Classifier: Topic :: Software Development :: Libraries :: Python Modules
